cloudshare/__init__.py
cloudshare/authentication_parameter_provider.py
cloudshare/hmacer.py
cloudshare/http.py
cloudshare/ioc.py
cloudshare/requester.py
cloudshare/token_generator.py
cloudshare/wrapper.py
cloudshare/wrapper_cls.py
cloudshare/test/__init__.py
cloudshare/test/test_authentication_parameter_provider.py
cloudshare/test/test_hmacer.py
cloudshare/test/test_integration.py
cloudshare/test/test_requester.py
cloudshare/test/test_token_generator.py
cloudshare-0.1.3.dist-info/LICENSE.txt
cloudshare-0.1.3.dist-info/METADATA
cloudshare-0.1.3.dist-info/WHEEL
cloudshare-0.1.3.dist-info/top_level.txt
cloudshare-0.1.3.dist-info/RECORD
