Metadata-Version: 2.1
Name: cloudshare
Version: 0.1.3
Summary: A python wrapper for the CloudShare REST API.
Home-page: https://github.com/cloudshare/cloudshare-py-sdk
Author: Jonathan Sadan
Author-email: Jonathan Sadan <jonathan@cloudshare.com>
Project-URL: Homepage, https://github.com/cloudshare/cloudshare-py-sdk
Project-URL: Bug Tracker, https://github.com/cloudshare/cloudshare-py-sdk/issues
Keywords: cloudshare,cloud,SDK,REST,API
Requires-Python: >=3.6
License-File: LICENSE.txt
